src/__init__.py
src/pkg_main_module.py
src/aws/__init__.py
src/aws/aws_supporter.py
src/aws/common/__init__.py
src/aws/common/_session.py
src/aws/common/paginator.py
src/aws/common/resource_map.py
src/aws/common/result_map.py
src/aws/common/service_handler_interface.py
src/aws/common/support.py
src/aws/service/__init__.py
src/aws/service/acm_handler.py
src/aws/service/cloudfront_handler.py
src/aws/service/cloudtrail_handler.py
src/aws/service/cloudwatch_handler.py
src/aws/service/codebuild_handler.py
src/aws/service/codecommit_handler.py
src/aws/service/codedeploy_handler.py
src/aws/service/codepipeline_handler.py
src/aws/service/directconnect_handler.py
src/aws/service/ec2_handler.py
src/aws/service/ecr_handler.py
src/aws/service/efs_handler.py
src/aws/service/elasticache_handler.py
src/aws/service/elb_handler.py
src/aws/service/fsx_handler.py
src/aws/service/globalaccelerator_handler.py
src/aws/service/rds_handler.py
src/aws/service/route53_handler.py
src/aws/service/s3_handler.py
src/aws/service/sts_handler.py
src/aws/service/vpc_handler.py
src/aws/service/workspaces_handler.py
src/common/__init__.py
src/common/_datetime.py
src/common/_dict.py
src/common/_logging.py
src/common/_os.py
src/common/_utill.py
src/common/convert.py
src/common/debug.py
src/common/power_point.py
jhoney_pkg-0.0.0.0.0.1.dist-info/METADATA
jhoney_pkg-0.0.0.0.0.1.dist-info/WHEEL
jhoney_pkg-0.0.0.0.0.1.dist-info/top_level.txt
jhoney_pkg-0.0.0.0.0.1.dist-info/RECORD
